.coveragerc
.mailmap
.testr.conf
AUTHORS
CONTRIBUTING.rst
ChangeLog
HACKING.rst
LICENSE
MANIFEST.in
README.rst
babel.cfg
openstack-common.conf
requirements.txt
setup.cfg
setup.py
test-requirements.txt
tox.ini
doc/source/api.rst
doc/source/conf.py
doc/source/contributing.rst
doc/source/history.rst
doc/source/index.rst
doc/source/installation.rst
doc/source/usage.rst
oslo.windows.egg-info/PKG-INFO
oslo.windows.egg-info/SOURCES.txt
oslo.windows.egg-info/dependency_links.txt
oslo.windows.egg-info/not-zip-safe
oslo.windows.egg-info/pbr.json
oslo.windows.egg-info/requires.txt
oslo.windows.egg-info/top_level.txt
oslo_windows/__init__.py
oslo_windows/_i18n.py
oslo_windows/_utils.py
oslo_windows/exceptions.py
oslo_windows/utilsfactory.py
oslo_windows/tests/__init__.py
oslo_windows/tests/test_utils.py
oslo_windows/tests/test_utilsfactory.py
oslo_windows/tests/utils/__init__.py
oslo_windows/tests/utils/test_basevolumeutils.py
oslo_windows/tests/utils/test_hostutils.py
oslo_windows/tests/utils/test_hostutilsv2.py
oslo_windows/tests/utils/test_ioutils.py
oslo_windows/tests/utils/test_jobutils.py
oslo_windows/tests/utils/test_livemigrationutils.py
oslo_windows/tests/utils/test_networkutils.py
oslo_windows/tests/utils/test_networkutilsv2.py
oslo_windows/tests/utils/test_pathutils.py
oslo_windows/tests/utils/test_rdpconsoleutils.py
oslo_windows/tests/utils/test_rdpconsoleutilsv2.py
oslo_windows/tests/utils/test_vhdutils.py
oslo_windows/tests/utils/test_vhdutilsv2.py
oslo_windows/tests/utils/test_vmutils.py
oslo_windows/tests/utils/test_vmutilsv2.py
oslo_windows/tests/utils/test_volumeutils.py
oslo_windows/tests/utils/test_volumeutilsv2.py
oslo_windows/utils/__init__.py
oslo_windows/utils/basevolumeutils.py
oslo_windows/utils/constants.py
oslo_windows/utils/hostutils.py
oslo_windows/utils/hostutilsv2.py
oslo_windows/utils/ioutils.py
oslo_windows/utils/jobutils.py
oslo_windows/utils/livemigrationutils.py
oslo_windows/utils/networkutils.py
oslo_windows/utils/networkutilsv2.py
oslo_windows/utils/pathutils.py
oslo_windows/utils/rdpconsoleutils.py
oslo_windows/utils/rdpconsoleutilsv2.py
oslo_windows/utils/vhdutils.py
oslo_windows/utils/vhdutilsv2.py
oslo_windows/utils/vmutils.py
oslo_windows/utils/vmutilsv2.py
